kis/__init__.py
kis/async_client.py
kis/auth.py
kis/calc.py
kis/client.py
kis/domestic.py
kis/errors.py
kis/overseas.py
kis/snapshot.py
kis/types.py
kis/utils.py
kis/ws.py
kis_wrapper-0.3.0.dist-info/METADATA
kis_wrapper-0.3.0.dist-info/WHEEL
kis_wrapper-0.3.0.dist-info/licenses/LICENSE
kis_wrapper-0.3.0.dist-info/RECORD
