Metadata-Version: 2.4
Name: kis-wrapper
Version: 0.3.0
Summary: Korea Investment & Securities API wrapper for Python
Project-URL: Homepage, https://github.com/LaytonAI/kis-wrapper
Project-URL: Documentation, https://github.com/LaytonAI/kis-wrapper#readme
Project-URL: Issues, https://github.com/LaytonAI/kis-wrapper/issues
License-Expression: MIT
License-File: LICENSE
Keywords: api,kis,korea-investment,stock,trading
Classifier: Development Status :: 4 - Beta
Classifier: Intended Audience :: Developers
Classifier: License :: OSI Approved :: MIT License
Classifier: Programming Language :: Python :: 3.11
Classifier: Programming Language :: Python :: 3.12
Classifier: Topic :: Office/Business :: Financial :: Investment
Requires-Python: >=3.11
Requires-Dist: httpx
Requires-Dist: pycryptodome
Requires-Dist: websockets
Provides-Extra: dev
Requires-Dist: mypy; extra == 'dev'
Requires-Dist: pytest; extra == 'dev'
Requires-Dist: pytest-asyncio; extra == 'dev'
Requires-Dist: pytest-httpx; extra == 'dev'
Requires-Dist: ruff; extra == 'dev'
